atttest/__init__.py
atttest/test.py
atttest-0.1.21.dist-info/METADATA
atttest-0.1.21.dist-info/WHEEL
atttest-0.1.21.dist-info/RECORD
